{
  "joining-game": [
    {
      "method": "POST",
      "url": "/api/v1/players/login",
      "requestBody": "{\n  \"password\": \"tbbt12\",\n  \"playerName\": \"leonard\"\n}",
      "responseStatus": 200,
      "responseBody": "{\n  \"playerName\": \"leonard\",\n  \"token\": \"73036093-b027-4d9f-90e0-9c55d9486027\",\n  \"message\": \"The leonard player has been logged successfully\"\n}",
      "handler": "com.tfg.game.players.api.PlayersApi#login(LoginForm)",
      "resolvedException": "null"
    },
    {
      "method": "POST",
      "url": "/api/v1/games/byPlayer",
      "requestBody": "{\n  \"playerName\": \"penny\"\n}",
      "responseStatus": 200,
      "responseBody": "{\n  \"games\": [\n    {\n      \"creatorName\": \"penny\",\n      \"gameName\": \"together\",\n      \"joinedPlayerNames\": [\n        \"penny\"\n      ]\n    }\n  ]\n}",
      "handler": "com.tfg.game.games.api.GamesApi#listGamesByCreator(ListGamesByCreatorForm)",
      "resolvedException": "null"
    },
    {
      "method": "POST",
      "url": "/api/v1/games/join",
      "requestBody": "{\n  \"gameName\": \"together\",\n  \"creatorName\": \"penny\",\n  \"token\": \"73036093-b027-4d9f-90e0-9c55d9486027\"\n}",
      "responseStatus": 200,
      "responseBody": "{\n  \"status\": 200,\n  \"message\": \"You have joined together game from penny successfully\"\n}",
      "handler": "com.tfg.game.games.api.GamesApi#join(JoinGameForm)",
      "resolvedException": "null"
    },
    {
      "method": "POST",
      "url": "/api/v1/games/byJoined",
      "requestBody": "{\n  \"token\": \"73036093-b027-4d9f-90e0-9c55d9486027\"\n}",
      "responseStatus": 200,
      "responseBody": "{\n  \"games\": [\n    {\n      \"creatorName\": \"penny\",\n      \"gameName\": \"together\",\n      \"joinedPlayerNames\": [\n        \"penny\",\n        \"leonard\"\n      ]\n    }\n  ]\n}",
      "handler": "com.tfg.game.games.api.GamesApi#listGamesByJoined(ListGamesByJoinedForm)",
      "resolvedException": "null"
    },
    {
      "method": "POST",
      "url": "/api/v1/games/byJoined",
      "requestBody": "{\n  \"token\": \"73036093-b027-4d9f-90e0-9c55d9486027\"\n}",
      "responseStatus": 200,
      "responseBody": "{\n  \"games\": [\n    {\n      \"creatorName\": \"penny\",\n      \"gameName\": \"together\",\n      \"joinedPlayerNames\": [\n        \"penny\",\n        \"leonard\"\n      ]\n    },\n    {\n      \"creatorName\": \"leonard\",\n      \"gameName\": \"alone\",\n      \"joinedPlayerNames\": [\n        \"leonard\"\n      ]\n    }\n  ]\n}",
      "handler": "com.tfg.game.games.api.GamesApi#listGamesByJoined(ListGamesByJoinedForm)",
      "resolvedException": "null"
    }
  ],
  "already-joined-games": [
    {
      "method": "POST",
      "url": "/api/v1/players/login",
      "requestBody": "{\n  \"password\": \"tbbt12\",\n  \"playerName\": \"leonard\"\n}",
      "responseStatus": 200,
      "responseBody": "{\n  \"playerName\": \"leonard\",\n  \"token\": \"f5dff07e-d5f4-46e2-8b21-67d198286248\",\n  \"message\": \"The leonard player has been logged successfully\"\n}",
      "handler": "com.tfg.game.players.api.PlayersApi#login(LoginForm)",
      "resolvedException": "null"
    },
    {
      "method": "POST",
      "url": "/api/v1/games/byPlayer",
      "requestBody": "{\n  \"playerName\": \"penny\"\n}",
      "responseStatus": 200,
      "responseBody": "{\n  \"games\": [\n    {\n      \"creatorName\": \"penny\",\n      \"gameName\": \"first\",\n      \"joinedPlayerNames\": [\n        \"penny\"\n      ]\n    },\n    {\n      \"creatorName\": \"penny\",\n      \"gameName\": \"second\",\n      \"joinedPlayerNames\": [\n        \"penny\"\n      ]\n    }\n  ]\n}",
      "handler": "com.tfg.game.games.api.GamesApi#listGamesByCreator(ListGamesByCreatorForm)",
      "resolvedException": "null"
    },
    {
      "method": "POST",
      "url": "/api/v1/games/join",
      "requestBody": "{\n  \"gameName\": \"first\",\n  \"creatorName\": \"penny\",\n  \"token\": \"f5dff07e-d5f4-46e2-8b21-67d198286248\"\n}",
      "responseStatus": 200,
      "responseBody": "{\n  \"status\": 200,\n  \"message\": \"You have joined first game from penny successfully\"\n}",
      "handler": "com.tfg.game.games.api.GamesApi#join(JoinGameForm)",
      "resolvedException": "null"
    },
    {
      "method": "POST",
      "url": "/api/v1/games/byPlayer",
      "requestBody": "{\n  \"playerName\": \"penny\"\n}",
      "responseStatus": 200,
      "responseBody": "{\n  \"games\": [\n    {\n      \"creatorName\": \"penny\",\n      \"gameName\": \"first\",\n      \"joinedPlayerNames\": [\n        \"penny\",\n        \"leonard\"\n      ]\n    },\n    {\n      \"creatorName\": \"penny\",\n      \"gameName\": \"second\",\n      \"joinedPlayerNames\": [\n        \"penny\"\n      ]\n    }\n  ]\n}",
      "handler": "com.tfg.game.games.api.GamesApi#listGamesByCreator(ListGamesByCreatorForm)",
      "resolvedException": "null"
    }
  ],
  "validations": [
    {
      "method": "POST",
      "url": "/api/v1/players/login",
      "requestBody": "{\n  \"password\": \"tbbt12\",\n  \"playerName\": \"leonard\"\n}",
      "responseStatus": 200,
      "responseBody": "{\n  \"playerName\": \"leonard\",\n  \"token\": \"8ffd7202-15e3-460d-969a-de098a1d2500\",\n  \"message\": \"The leonard player has been logged successfully\"\n}",
      "handler": "com.tfg.game.players.api.PlayersApi#login(LoginForm)",
      "resolvedException": "null"
    },
    {
      "method": "POST",
      "url": "/api/v1/games/byPlayer",
      "requestBody": "{\n  \"playerName\": \"\"\n}",
      "responseStatus": 400,
      "responseBody": "{\n  \"isError\": true,\n  \"message\": \"The friend name should be present\"\n}",
      "handler": "com.tfg.game.games.api.GamesApi#listGamesByCreator(ListGamesByCreatorForm)",
      "resolvedException": "The friend name should be present\njava.io.PrintWriter@2aa811f9"
    },
    {
      "method": "POST",
      "url": "/api/v1/games/byPlayer",
      "requestBody": "{\n  \"playerName\": \"unexisting\"\n}",
      "responseStatus": 400,
      "responseBody": "{\n  \"isError\": true,\n  \"message\": \"The friend name should be an existing player\"\n}",
      "handler": "com.tfg.game.games.api.GamesApi#listGamesByCreator(ListGamesByCreatorForm)",
      "resolvedException": "The friend name should be an existing player\njava.io.PrintWriter@4b7e4d14"
    },
    {
      "method": "POST",
      "url": "/api/v1/games/byPlayer",
      "requestBody": "{\n  \"playerName\": \"sheldon\"\n}",
      "responseStatus": 200,
      "responseBody": "{\n  \"games\": []\n}",
      "handler": "com.tfg.game.games.api.GamesApi#listGamesByCreator(ListGamesByCreatorForm)",
      "resolvedException": "null"
    },
    {
      "method": "POST",
      "url": "/api/v1/games/byPlayer",
      "requestBody": "{\n  \"playerName\": \"leonard\"\n}",
      "responseStatus": 200,
      "responseBody": "{\n  \"games\": [\n    {\n      \"creatorName\": \"leonard\",\n      \"gameName\": \"mygame\",\n      \"joinedPlayerNames\": [\n        \"leonard\"\n      ]\n    }\n  ]\n}",
      "handler": "com.tfg.game.games.api.GamesApi#listGamesByCreator(ListGamesByCreatorForm)",
      "resolvedException": "null"
    },
    {
      "method": "POST",
      "url": "/api/v1/games/join",
      "requestBody": "{\n  \"gameName\": \"mygame\",\n  \"creatorName\": \"leonard\",\n  \"token\": \"8ffd7202-15e3-460d-969a-de098a1d2500\"\n}",
      "responseStatus": 400,
      "responseBody": "{\n  \"isError\": true,\n  \"message\": \"You should join games in which are you not joined\"\n}",
      "handler": "com.tfg.game.games.api.GamesApi#join(JoinGameForm)",
      "resolvedException": "You should join games in which are you not joined\njava.io.PrintWriter@737ff5c4"
    },
    {
      "method": "POST",
      "url": "/api/v1/games/byPlayer",
      "requestBody": "{\n  \"playerName\": \"penny\"\n}",
      "responseStatus": 200,
      "responseBody": "{\n  \"games\": [\n    {\n      \"creatorName\": \"penny\",\n      \"gameName\": \"first\",\n      \"joinedPlayerNames\": [\n        \"penny\"\n      ]\n    },\n    {\n      \"creatorName\": \"penny\",\n      \"gameName\": \"second\",\n      \"joinedPlayerNames\": [\n        \"penny\"\n      ]\n    }\n  ]\n}",
      "handler": "com.tfg.game.games.api.GamesApi#listGamesByCreator(ListGamesByCreatorForm)",
      "resolvedException": "null"
    },
    {
      "method": "POST",
      "url": "/api/v1/games/join",
      "requestBody": "{\n  \"gameName\": \"first\",\n  \"creatorName\": \"penny\",\n  \"token\": \"8ffd7202-15e3-460d-969a-de098a1d2500\"\n}",
      "responseStatus": 200,
      "responseBody": "{\n  \"status\": 200,\n  \"message\": \"You have joined first game from penny successfully\"\n}",
      "handler": "com.tfg.game.games.api.GamesApi#join(JoinGameForm)",
      "resolvedException": "null"
    },
    {
      "method": "POST",
      "url": "/api/v1/games/byPlayer",
      "requestBody": "{\n  \"playerName\": \"penny\"\n}",
      "responseStatus": 200,
      "responseBody": "{\n  \"games\": [\n    {\n      \"creatorName\": \"penny\",\n      \"gameName\": \"first\",\n      \"joinedPlayerNames\": [\n        \"penny\",\n        \"leonard\"\n      ]\n    },\n    {\n      \"creatorName\": \"penny\",\n      \"gameName\": \"second\",\n      \"joinedPlayerNames\": [\n        \"penny\"\n      ]\n    }\n  ]\n}",
      "handler": "com.tfg.game.games.api.GamesApi#listGamesByCreator(ListGamesByCreatorForm)",
      "resolvedException": "null"
    },
    {
      "method": "POST",
      "url": "/api/v1/games/join",
      "requestBody": "{\n  \"gameName\": \"first\",\n  \"creatorName\": \"penny\",\n  \"token\": \"8ffd7202-15e3-460d-969a-de098a1d2500\"\n}",
      "responseStatus": 400,
      "responseBody": "{\n  \"isError\": true,\n  \"message\": \"You should join games in which are you not joined\"\n}",
      "handler": "com.tfg.game.games.api.GamesApi#join(JoinGameForm)",
      "resolvedException": "You should join games in which are you not joined\njava.io.PrintWriter@3cf70afa"
    }
  ]
}